README.rst
setup.py
django_yandex_cash_register.egg-info/PKG-INFO
django_yandex_cash_register.egg-info/SOURCES.txt
django_yandex_cash_register.egg-info/SOURCES.txt.py
django_yandex_cash_register.egg-info/dependency_links.txt
django_yandex_cash_register.egg-info/dependency_links.txt.py
django_yandex_cash_register.egg-info/not-zip-safe
django_yandex_cash_register.egg-info/requires.txt
django_yandex_cash_register.egg-info/requires.txt.py
django_yandex_cash_register.egg-info/top_level.txt
django_yandex_cash_register.egg-info/top_level.txt.py
yandex_cash_register/__init__.py
yandex_cash_register/admin.py
yandex_cash_register/apps.py
yandex_cash_register/conf.py
yandex_cash_register/forms.py
yandex_cash_register/interfaces.py
yandex_cash_register/models.py
yandex_cash_register/signals.py
yandex_cash_register/urls.py
yandex_cash_register/views.py
yandex_cash_register/locale/ru/LC_MESSAGES/django.po
yandex_cash_register/migrations/0001_initial.py
yandex_cash_register/migrations/0002_auto_20160810_1629.py
yandex_cash_register/migrations/0003_auto_20160810_1756.py
yandex_cash_register/migrations/0004_auto_20170206_2146.py
yandex_cash_register/migrations/__init__.py
yandex_cash_register/templates/yandex_cash_register/finish_payment.html
yandex_cash_register/tests/__init__.py
yandex_cash_register/tests/runtests.py
yandex_cash_register/tests/test_forms.py
yandex_cash_register/tests/test_models.py
yandex_cash_register/tests/test_views.py
yandex_cash_register/tests/urls.py